{
  "info": {
    "author": "Maxwell Conradt",
    "author_email": "mhconradt@protonmail.com",
    "bugtrack_url": null,
    "classifiers": [
      "License :: OSI Approved :: MIT License",
      "Operating System :: OS Independent",
      "Programming Language :: Python :: 3"
    ],
    "description": "This allows you to visualize the bytecode of a cell in IPython upon running it.\n\n## Installation\n\n    pip3 install dis-magic\n\nTo manually load, run the following in your IPython prompt:\n    \n    %load_ext dis_magic\n\nTo automatically load, add the following to your [IPython configuration file](https://ipython.org/ipython-doc/3/config/intro.html):\n    \n    c = get_config()\n    c.InteractiveShellApp.extensions.append('dis_magic')\n    \n## Usage\n\nVerifying Python follows PEMDAS:\n\n    In [6]: %dis foo = 6 ** 2 + 6\n      1           0 LOAD_CONST               0 (42)\n                  2 STORE_NAME               0 (foo)\n                  4 LOAD_CONST               1 (None)\n                  6 RETURN_VALUE\n        \nYou can use it in a cell too:\n\n    In [4]: %%dis\n       ...:\n       ...: def fibonacci(n: int) -> int:\n       ...:     if n <= 1: return 1\n       ...:     return fibonacci(n - 2) + fibonacci(n - 1)\n       ...:\n      2           0 LOAD_NAME                0 (int)\n                  2 LOAD_NAME                0 (int)\n                  4 LOAD_CONST               0 (('n', 'return'))\n                  6 BUILD_CONST_KEY_MAP      2\n                  8 LOAD_CONST               1 (<code object fibonacci at 0x111457b30, file \"<dis>\", line 2>)\n                 10 LOAD_CONST               2 ('fibonacci')\n                 12 MAKE_FUNCTION            4 (annotations)\n                 14 STORE_NAME               1 (fibonacci)\n                 16 LOAD_CONST               3 (None)\n                 18 RETURN_VALUE\n    \n    Disassembly of <code object fibonacci at 0x111457b30, file \"<dis>\", line 2>:\n      3           0 LOAD_FAST                0 (n)\n                  2 LOAD_CONST               1 (1)\n                  4 COMPARE_OP               1 (<=)\n                  6 POP_JUMP_IF_FALSE       12\n                  8 LOAD_CONST               1 (1)\n                 10 RETURN_VALUE\n    \n      4     >>   12 LOAD_GLOBAL              0 (fibonacci)\n                 14 LOAD_FAST                0 (n)\n                 16 LOAD_CONST               2 (2)\n                 18 BINARY_SUBTRACT\n                 20 CALL_FUNCTION            1\n                 22 LOAD_GLOBAL              0 (fibonacci)\n                 24 LOAD_FAST                0 (n)\n                 26 LOAD_CONST               1 (1)\n                 28 BINARY_SUBTRACT\n                 30 CALL_FUNCTION            1\n                 32 BINARY_ADD\n                 34 RETURN_VALUE\n\n",
    "description_content_type": "text/markdown",
    "docs_url": null,
    "download_url": "",
    "downloads": {
      "last_day": -1,
      "last_month": -1,
      "last_week": -1
    },
    "home_page": "https://github.com/mhconradt/dis-magic",
    "keywords": "",
    "license": "",
    "maintainer": "",
    "maintainer_email": "",
    "name": "dis-magic",
    "package_url": "https://pypi.org/project/dis-magic/",
    "platform": "",
    "project_url": "https://pypi.org/project/dis-magic/",
    "project_urls": {
      "Homepage": "https://github.com/mhconradt/dis-magic"
    },
    "release_url": "https://pypi.org/project/dis-magic/1.0.0/",
    "requires_dist": [
      "IPython"
    ],
    "requires_python": ">=3.6",
    "summary": "IPython extension allowing visualizing bytecode of cell using magic",
    "version": "1.0.0",
    "yanked": false,
    "yanked_reason": null
  },
  "last_serial": 12197669,
  "releases": {
    "1.0.0": [
      {
        "comment_text": "",
        "digests": {
          "blake2b_256": "13a29119d75e55e0ac39414f255f0c3edc674074ab0c5d55f1d5bb5c36828167",
          "md5": "cd4b74690274266bea9019f3abfce5b1",
          "sha256": "7a30dc4ab145868aa1676e5f6f0561e73ca794e6ca10545ad90ed77fcb66ef31"
        },
        "downloads": -1,
        "filename": "dis_magic-1.0.0-py3-none-any.whl",
        "has_sig": false,
        "md5_digest": "cd4b74690274266bea9019f3abfce5b1",
        "packagetype": "bdist_wheel",
        "python_version": "py3",
        "requires_python": ">=3.6",
        "size": 2296,
        "upload_time": "2021-12-03T04:40:40",
        "upload_time_iso_8601": "2021-12-03T04:40:40.919922Z",
        "url": "https://files.pythonhosted.org/packages/13/a2/9119d75e55e0ac39414f255f0c3edc674074ab0c5d55f1d5bb5c36828167/dis_magic-1.0.0-py3-none-any.whl",
        "yanked": false,
        "yanked_reason": null
      },
      {
        "comment_text": "",
        "digests": {
          "blake2b_256": "a91791ff1e28bc580a13520fdb4b0c865456653c6c86657032ebf3a44eda26fd",
          "md5": "0c6d63741430fee8453c651d7bf752da",
          "sha256": "14b271b8044430b16f20c3fefa5e1f2645eb0f2ede6962b085d96b8597388eec"
        },
        "downloads": -1,
        "filename": "dis-magic-1.0.0.tar.gz",
        "has_sig": false,
        "md5_digest": "0c6d63741430fee8453c651d7bf752da",
        "packagetype": "sdist",
        "python_version": "source",
        "requires_python": ">=3.6",
        "size": 2287,
        "upload_time": "2021-12-03T04:40:42",
        "upload_time_iso_8601": "2021-12-03T04:40:42.305660Z",
        "url": "https://files.pythonhosted.org/packages/a9/17/91ff1e28bc580a13520fdb4b0c865456653c6c86657032ebf3a44eda26fd/dis-magic-1.0.0.tar.gz",
        "yanked": false,
        "yanked_reason": null
      }
    ]
  },
  "urls": [
    {
      "comment_text": "",
      "digests": {
        "blake2b_256": "13a29119d75e55e0ac39414f255f0c3edc674074ab0c5d55f1d5bb5c36828167",
        "md5": "cd4b74690274266bea9019f3abfce5b1",
        "sha256": "7a30dc4ab145868aa1676e5f6f0561e73ca794e6ca10545ad90ed77fcb66ef31"
      },
      "downloads": -1,
      "filename": "dis_magic-1.0.0-py3-none-any.whl",
      "has_sig": false,
      "md5_digest": "cd4b74690274266bea9019f3abfce5b1",
      "packagetype": "bdist_wheel",
      "python_version": "py3",
      "requires_python": ">=3.6",
      "size": 2296,
      "upload_time": "2021-12-03T04:40:40",
      "upload_time_iso_8601": "2021-12-03T04:40:40.919922Z",
      "url": "https://files.pythonhosted.org/packages/13/a2/9119d75e55e0ac39414f255f0c3edc674074ab0c5d55f1d5bb5c36828167/dis_magic-1.0.0-py3-none-any.whl",
      "yanked": false,
      "yanked_reason": null
    },
    {
      "comment_text": "",
      "digests": {
        "blake2b_256": "a91791ff1e28bc580a13520fdb4b0c865456653c6c86657032ebf3a44eda26fd",
        "md5": "0c6d63741430fee8453c651d7bf752da",
        "sha256": "14b271b8044430b16f20c3fefa5e1f2645eb0f2ede6962b085d96b8597388eec"
      },
      "downloads": -1,
      "filename": "dis-magic-1.0.0.tar.gz",
      "has_sig": false,
      "md5_digest": "0c6d63741430fee8453c651d7bf752da",
      "packagetype": "sdist",
      "python_version": "source",
      "requires_python": ">=3.6",
      "size": 2287,
      "upload_time": "2021-12-03T04:40:42",
      "upload_time_iso_8601": "2021-12-03T04:40:42.305660Z",
      "url": "https://files.pythonhosted.org/packages/a9/17/91ff1e28bc580a13520fdb4b0c865456653c6c86657032ebf3a44eda26fd/dis-magic-1.0.0.tar.gz",
      "yanked": false,
      "yanked_reason": null
    }
  ],
  "vulnerabilities": []
}